pycinante/__init__.py
pycinante/utils.py
pycinante/dict/__init__.py
pycinante/dict/attrdict.py
pycinante/io/__init__.py
pycinante/io/accessor.py
pycinante/io/file.py
pycinante/io/path.py
pycinante/io/utils.py
pycinante/log/__init__.py
pycinante/log/logger.py
pycinante/log/utils.py
pycinante/misc/__init__.py
pycinante/misc/deprecated.py
pycinante/misc/unit.py
pycinante/misc/version.py
pycinante/stream/__init__.py
pycinante/stream/pystream.py
pycinante/stream/utils.py
tests/__init__.py
tests/test_attrdict.py
tests/test_file.py
tests/test_logger.py
tests/test_stream.py
pycinante-0.0.4.dist-info/LICENSE
pycinante-0.0.4.dist-info/METADATA
pycinante-0.0.4.dist-info/WHEEL
pycinante-0.0.4.dist-info/top_level.txt
pycinante-0.0.4.dist-info/zip-safe
pycinante-0.0.4.dist-info/RECORD
