Metadata-Version: 2.1
Name: pycinante
Version: 0.0.4
Summary: Python rocinante (Pycinante) for easily programming in Python.
Home-page: https://github.com/gndlwch2w/pycinante
Author: Chisheng Chen
Author-email: chishengchen@126.com
License: MIT-0
Platform: UNKNOWN
Requires-Python: >=3.8
License-File: LICENSE
Requires-Dist: setuptools
Requires-Dist: loguru
Requires-Dist: loguru-mypy
Requires-Dist: typing-extensions
